setup.py
SparseMatrixTools/__init__.py
SparseMatrixTools.egg-info/PKG-INFO
SparseMatrixTools.egg-info/SOURCES.txt
SparseMatrixTools.egg-info/dependency_links.txt
SparseMatrixTools.egg-info/not-zip-safe
SparseMatrixTools.egg-info/top_level.txt