Metadata-Version: 1.0
Name: SparseMatrixTools
Version: 0.1
Summary: Sparse Matrix Operations tools
Home-page: https://github.com/hawk31/SparseMatrixTools
Author: José Jiménez
Author-email: jose@jimenezluna.com
License: MIT
Platform: UNKNOWN
